django_wishlist-1.0.dist-info/DESCRIPTION.rst
django_wishlist-1.0.dist-info/METADATA
django_wishlist-1.0.dist-info/RECORD
django_wishlist-1.0.dist-info/WHEEL
django_wishlist-1.0.dist-info/metadata.json
django_wishlist-1.0.dist-info/pbr.json
django_wishlist-1.0.dist-info/top_level.txt
wishlist/__init__.py
wishlist/admin.py
wishlist/context_processors.py
wishlist/forms.py
wishlist/managers.py
wishlist/models.py
wishlist/settings.py
wishlist/urls.py
wishlist/utils.py
wishlist/views.py
wishlist/locale/en/LC_MESSAGES/django.mo
wishlist/locale/en/LC_MESSAGES/django.po
wishlist/locale/en_US/LC_MESSAGES/django.po
wishlist/locale/nl/LC_MESSAGES/django.mo
wishlist/locale/nl/LC_MESSAGES/django.po
wishlist/templates/base.html
wishlist/templates/wishlist/wishlistitem_add_form.html
wishlist/templates/wishlist/wishlistitem_confirm_clear.html
wishlist/templates/wishlist/wishlistitem_confirm_delete.html
wishlist/templates/wishlist/wishlistitem_form.html
wishlist/templates/wishlist/wishlistitem_list.html
wishlist/templates/wishlist/wishlistitem_remove_form.html
wishlist/templatetags/__init__.py
wishlist/templatetags/wishlist_tags.py
