Metadata-Version: 2.0
Name: django-wishlist
Version: 1.0
Summary: Generic user wishlists for use with any Django model.
Home-page: https://github.com/dokterbob/django-wishlist/
Author: Mathijs de Bruin
Author-email: mathijs@mathijsfietst.nl
License: AGPL
Platform: UNKNOWN
Classifier: Development Status :: 5 - Production/Stable
Classifier: Environment :: Web Environment
Classifier: Framework :: Django
Classifier: Intended Audience :: Developers
Classifier: License :: OSI Approved :: GNU Affero General Public License v3
Classifier: Operating System :: OS Independent
Classifier: Programming Language :: Python
Classifier: Topic :: Utilities
Requires-Dist: Django (>=1.8.13)
